__init__.py
parallel/__init__.py
zbuild/__init__.py
zbuild_tools-1.0.28.dist-info/METADATA
zbuild_tools-1.0.28.dist-info/WHEEL
zbuild_tools-1.0.28.dist-info/entry_points.txt
zbuild_tools-1.0.28.dist-info/top_level.txt
zbuild_tools-1.0.28.dist-info/RECORD
