Metadata-Version: 2.4
Name: zbuild-tools
Version: 1.0.28
Summary: It is the build system of linux which is based on Conan
Author-email: "Zhiguo.Zhu" <294966@qq.com>
Requires-Python: <=3.14,>=3.8
Requires-Dist: conan-zbuild<2.0.0,>=1.66.3
Requires-Dist: dockerpty==0.4.1
Requires-Dist: docker==7.1.0
Requires-Dist: intervaltree==3.1.0
Requires-Dist: pyelftools
Requires-Dist: ruamel.yaml==0.18.15
Requires-Dist: psutil
Requires-Dist: pyserial==3.5
Requires-Dist: fbtftp==0.5
Requires-Dist: dohq-artifactory==1.0.1
Requires-Dist: aiohttp
Requires-Dist: easy_enum==0.3.0
Requires-Dist: paramiko==3.5.0
Requires-Dist: pytest
Requires-Dist: tblib
Requires-Dist: shenaniganfs
